{
  "metadata": {
    "generated_at": "2026-05-01T04:45:57.789127",
    "total_news": 50,
    "last_updated": "2026-05-01T04:45:57.789134",
    "version": "2.0",
    "compatible_with": "NewsSection.tsx"
  },
  "news": {
    "all_articles": [],
    "news": [],
    "interview": [
      {
        "title": "Isaiah Rashad Links Up With SZA for New Song “Boy in Red”",
        "summary": "Isaiah와 관련된 주요 음악 업계 소식이 전해졌다. Isaiah Rashad Links Up With SZA for New Song “Boy in Red”",
        "url": "https://pitchfork.com/news/isaiah-rashad-links-up-with-sza-for-new-song-boy-in-red/",
        "published_date": "2026-05-01 04:14:48",
        "category": "interview",
        "source": "pitchfork.com"
      },
      {
        "title": "Lizzo Is 100% That ‘Bitch’ on Upcoming Album’s Bold Title Track: Stream It Now",
        "summary": "Lizzo와 관련된 주요 음악 업계 소식이 전해졌다. Lizzo Is 100% That ‘Bitch’ on Upcoming Album’s Bold Title Tr...",
        "url": "https://www.billboard.com/music/pop/lizzo-bitch-new-song-album-title-track-1236235864/",
        "published_date": "2026-05-01 04:05:46",
        "category": "interview",
        "source": "www.billboard.com"
      },
      {
        "title": "Listen to Two More Lady Gaga Songs From The Devil Wears Prada 2",
        "summary": "Listen와 관련된 주요 음악 업계 소식이 전해졌다. Listen to Two More Lady Gaga Songs From The Devil Wears Prad...",
        "url": "https://pitchfork.com/news/listen-to-two-more-lady-gaga-songs-from-the-devil-wears-prada-2/",
        "published_date": "2026-05-01 04:05:29",
        "category": "interview",
        "source": "pitchfork.com"
      },
      {
        "title": "Kacey Musgraves Finds Herself In The ‘Middle of Nowhere’: Stream It Now",
        "summary": "Kacey와 관련된 주요 음악 업계 소식이 전해졌다. Kacey Musgraves Finds Herself In The ‘Middle of Nowhere’: St...",
        "url": "https://www.billboard.com/music/country/kacey-musgraves-middle-of-nowhere-album-stream-1236236498/",
        "published_date": "2026-05-01 04:02:59",
        "category": "interview",
        "source": "www.billboard.com"
      },
      {
        "title": "The ‘Devil Wears Prada 2’ Soundtrack Is Ready for the Runway: Stream It Now",
        "summary": "The와 관련된 주요 음악 업계 소식이 전해졌다. The ‘Devil Wears Prada 2’ Soundtrack Is Ready for the Runway...",
        "url": "https://www.billboard.com/music/pop/devil-wears-prada-2-soundtrack-lady-gaga-stream-it-now-1236235846/",
        "published_date": "2026-05-01 04:01:12",
        "category": "interview",
        "source": "www.billboard.com"
      },
      {
        "title": "Here Are the (Suddenly Wealthy) 2026 Recipients of the Doris Duke Artist Awards, Who Each Receive a $525K Cash Prize",
        "summary": "Here와 관련된 주요 음악 업계 소식이 전해졌다. Here Are the (Suddenly Wealthy) 2026 Recipients of the Doris...",
        "url": "https://www.billboard.com/music/awards/doris-duke-artist-awards-2026-recipients-1236235996/",
        "published_date": "2026-05-01 04:01:00",
        "category": "interview",
        "source": "www.billboard.com"
      },
      {
        "title": "Kacey Musgraves’ ‘Middle of Nowhere’: All 13 Tracks Ranked",
        "summary": "Kacey와 관련된 주요 음악 업계 소식이 전해졌다. Kacey Musgraves’ ‘Middle of Nowhere’: All 13 Tracks Ranked",
        "url": "https://www.billboard.com/lists/kacey-musgraves-middle-of-nowhere-all-songs-ranked/",
        "published_date": "2026-05-01 04:01:00",
        "category": "interview",
        "source": "www.billboard.com"
      },
      {
        "title": "Denzel Curry to Headline Sydney’s Slam Dance",
        "summary": "Denzel와 관련된 주요 음악 업계 소식이 전해졌다. Denzel Curry to Headline Sydney’s Slam Dance",
        "url": "https://www.billboard.com/music/rb-hip-hop/denzel-curry-headline-sydney-slam-dance-1236236570/",
        "published_date": "2026-05-01 03:50:30",
        "category": "interview",
        "source": "www.billboard.com"
      },
      {
        "title": "Amy Allen Wins Pop Music Songwriter of the Year at 2026 ASCAP Pop Music Awards",
        "summary": "Amy Allen가 새로운 싱글을 발표했다. 새 곡은 아티스트의 음악적 진화를 보여주는 작품으로 평가받고 있다.",
        "url": "https://www.billboard.com/pro/2026-ascap-pop-awards-recap-amy-allen-sony-music-publishing/",
        "published_date": "2026-05-01 03:30:00",
        "category": "interview",
        "source": "www.billboard.com"
      },
      {
        "title": "Two Venues, a Bowling Alley & Jack White’s Stamp of Approval: How Detroit’s Majestic Theatre Center Became a Landmark",
        "summary": "Two와 관련된 주요 음악 업계 소식이 전해졌다. Two Venues, a Bowling Alley & Jack White’s Stamp of Approval...",
        "url": "https://www.billboard.com/pro/indie-venue-of-month-april-2026-detroit-majestic-theatre/",
        "published_date": "2026-05-01 01:58:13",
        "category": "interview",
        "source": "www.billboard.com"
      },
      {
        "title": "Olivia Rodrigo Kills Ashley Padilla In Her SNL Promos",
        "summary": "Olivia와 관련된 주요 음악 업계 소식이 전해졌다. Olivia Rodrigo Kills Ashley Padilla In Her SNL Promos",
        "url": "https://stereogum.com/2497560/olivia-rodrigo-kills-ashley-padilla-in-her-snl-promos/news/",
        "published_date": "2026-05-01 01:48:02",
        "category": "interview",
        "source": "www.stereogum.com"
      },
      {
        "title": "Spotify Users Can’t Sue Over Discovery Mode ‘Payola’ Accusations, Judge Says",
        "summary": "Spotify와 관련된 주요 음악 업계 소식이 전해졌다. Spotify Users Can’t Sue Over Discovery Mode ‘Payola’ Accusat...",
        "url": "https://www.billboard.com/pro/spotify-lawsuit-users-cant-sue-discovery-mode-payola/",
        "published_date": "2026-05-01 01:28:46",
        "category": "interview",
        "source": "www.billboard.com"
      },
      {
        "title": "‘Bluey’ Bounds Onto Kid Albums Chart With Orchestral Release ‘Up Here’",
        "summary": "‘Bluey’가 음악 차트에서 주목할 만한 성과를 기록했다. 상업적 성공을 입증하는 결과다.",
        "url": "https://www.billboard.com/music/chart-beat/bluey-up-here-orchestral-album-billboard-chart-debut-1236236512/",
        "published_date": "2026-05-01 01:11:58",
        "category": "interview",
        "source": "www.billboard.com"
      },
      {
        "title": "Squid’s Anton Pearson Announces Debut Album Driving Through Belgium: Hear “Tintinnabulation I”",
        "summary": "Squid’s Anton가 새 앨범 발매 소식을 공개했다. 이번 릴리스는 팬들과 음악 업계의 큰 관심을 받고 있다.",
        "url": "https://stereogum.com/2497550/squids-anton-pearson-announces-debut-album-driving-through-belgium-hear-tintinnabulation-i/music/",
        "published_date": "2026-05-01 01:01:06",
        "category": "interview",
        "source": "www.stereogum.com"
      },
      {
        "title": "Watch The Magnetic Fields and Fleet Foxes Perform “Book of Love” Together",
        "summary": "Watch와 관련된 주요 음악 업계 소식이 전해졌다. Watch The Magnetic Fields and Fleet Foxes Perform “Book of L...",
        "url": "https://pitchfork.com/news/watch-the-magnetic-fields-and-fleet-foxes-perform-book-of-love-together/",
        "published_date": "2026-05-01 00:49:45",
        "category": "interview",
        "source": "pitchfork.com"
      },
      {
        "title": "Stephin Merritt – One Of NYTimes’ Greatest Living American Songwriters – Sings With Robin Pecknold On East Village Radio",
        "summary": "Stephin Merritt가 새 앨범 발매 소식을 공개했다. 이번 릴리스는 팬들과 음악 업계의 큰 관심을 받고 있다.",
        "url": "https://stereogum.com/2497545/stephin-merritt-one-of-nytimes-greatest-living-american-songwriters-sings-with-robin-pecknold-on-east-village-radio/news/",
        "published_date": "2026-05-01 00:13:12",
        "category": "interview",
        "source": "www.stereogum.com"
      },
      {
        "title": "Madonna – “Bring Your Love” (Feat. Sabrina Carpenter)",
        "summary": "Madonna의 새로운 협업 프로젝트 소식이 공개되었다. 음악 팬들의 기대감이 높아지고 있다.",
        "url": "https://stereogum.com/2497517/madonna-bring-your-love-feat-sabrina-carpenter/music/",
        "published_date": "2026-04-30 22:55:43",
        "category": "interview",
        "source": "www.stereogum.com"
      },
      {
        "title": "Love On The Spectrum Stars Are Breaking Into The Music World",
        "summary": "Love와 관련된 주요 음악 업계 소식이 전해졌다. Love On The Spectrum Stars Are Breaking Into The Music World",
        "url": "https://stereogum.com/2497535/love-on-the-spectrum-stars-are-breaking-into-the-music-world/news/",
        "published_date": "2026-04-30 22:49:18",
        "category": "interview",
        "source": "www.stereogum.com"
      },
      {
        "title": "Jason Derulo Testifies Guitarist ‘Created Absolutely Nothing’ on ‘Savage Love’",
        "summary": "Jason와 관련된 주요 음악 업계 소식이 전해졌다. Jason Derulo Testifies Guitarist ‘Created Absolutely Nothing...",
        "url": "https://www.rollingstone.com/music/music-news/jason-derulo-producer-testifies-trial-1235556410/",
        "published_date": "2026-04-30 22:35:57",
        "category": "interview",
        "source": "www.rollingstone.com"
      },
      {
        "title": "Fugees Rapper Pras Turns Himself In to Begin 14-Year Sentence",
        "summary": "Fugees와 관련된 주요 음악 업계 소식이 전해졌다. Fugees Rapper Pras Turns Himself In to Begin 14-Year Sentenc...",
        "url": "https://www.rollingstone.com/music/music-news/pras-michel-fugees-turning-himself-in-1235556394/",
        "published_date": "2026-04-30 22:26:47",
        "category": "interview",
        "source": "www.rollingstone.com"
      },
      {
        "title": "Madonna and Sabrina Carpenter Unveil New Song “Bring Your Love”",
        "summary": "Madonna와 관련된 주요 음악 업계 소식이 전해졌다. Madonna and Sabrina Carpenter Unveil New Song “Bring Your Lo...",
        "url": "https://pitchfork.com/news/madonna-and-sabrina-carpenter-unveil-new-song-bring-your-love/",
        "published_date": "2026-04-30 22:10:09",
        "category": "interview",
        "source": "pitchfork.com"
      },
      {
        "title": "Madonna and Sabrina Carpenter Join Forces on New Song “Bring Your Love”: Stream",
        "summary": "Madonna와 관련된 주요 음악 업계 소식이 전해졌다. Madonna and Sabrina Carpenter Join Forces on New Song “Bring...",
        "url": "https://consequence.net/2026/04/madonna-sabrina-carpenter-bring-your-love-stream/",
        "published_date": "2026-04-30 22:01:51",
        "category": "interview",
        "source": "consequenceofsound.net"
      },
      {
        "title": "Mining Metal: Ain Sof Aur, Astral Spectre, Devoid of Thought, Lynx, Nagött, Ordh, Scimitar, Ultha",
        "summary": "Mining와 관련된 주요 음악 업계 소식이 전해졌다. Mining Metal: Ain Sof Aur, Astral Spectre, Devoid of Thought...",
        "url": "https://consequence.net/2026/04/mining-metal-april-2026/",
        "published_date": "2026-04-30 21:32:57",
        "category": "interview",
        "source": "consequenceofsound.net"
      },
      {
        "title": "Britney Spears Charged With Driving Under the Influence",
        "summary": "Britney와 관련된 주요 음악 업계 소식이 전해졌다. Britney Spears Charged With Driving Under the Influence",
        "url": "https://www.rollingstone.com/music/music-news/britney-spears-criminal-charge-dui-arrest-1235556372/",
        "published_date": "2026-04-30 20:55:32",
        "category": "interview",
        "source": "www.rollingstone.com"
      },
      {
        "title": "Foo Fighters face zombie apocalypse in gory new ‘Spit Shine’ video, directed by Dave Grohl",
        "summary": "Foo와 관련된 주요 음악 업계 소식이 전해졌다. Foo Fighters face zombie apocalypse in gory new ‘Spit Shine’...",
        "url": "https://www.nme.com/news/music/foo-fighters-face-zombie-apocalypse-in-gory-new-spit-shine-video-directed-by-dave-grohl-3943426?utm_source=rss&utm_medium=rss&utm_campaign=foo-fighters-face-zombie-apocalypse-in-gory-new-spit-shine-video-directed-by-dave-grohl",
        "published_date": "2026-04-30 20:49:36",
        "category": "interview",
        "source": "www.nme.com"
      },
      {
        "title": "Busta Rhymes Settles With Ex-Assistant Over ‘Defamatory’ Assault Claims",
        "summary": "Busta와 관련된 주요 음악 업계 소식이 전해졌다. Busta Rhymes Settles With Ex-Assistant Over ‘Defamatory’ Ass...",
        "url": "https://www.rollingstone.com/music/music-news/busta-rhymes-settles-assistant-assault-claims-1235556309/",
        "published_date": "2026-04-30 20:29:01",
        "category": "interview",
        "source": "www.rollingstone.com"
      },
      {
        "title": "Premature Evaluation: Kacey Musgraves Middle Of Nowhere",
        "summary": "Premature Evaluation:와 관련된 주요 음악 업계 소식이 전해졌다. Premature Evaluation: Kacey Musgraves Middle Of Nowhere",
        "url": "https://stereogum.com/2497402/premature-evaluation-kacey-musgraves-middle-of-nowhere/reviews/premature-evaluation/",
        "published_date": "2026-04-30 20:09:32",
        "category": "interview",
        "source": "www.stereogum.com"
      },
      {
        "title": "Terminator 2: Judgment Day Returning to Theaters This May",
        "summary": "Terminator와 관련된 주요 음악 업계 소식이 전해졌다. Terminator 2: Judgment Day Returning to Theaters This May",
        "url": "https://consequence.net/2026/04/terminator-2-judgement-day-re-release/",
        "published_date": "2026-04-30 19:47:19",
        "category": "interview",
        "source": "consequenceofsound.net"
      },
      {
        "title": "PinkPantheress Met Her Opp At Disney World",
        "summary": "PinkPantheress와 관련된 주요 음악 업계 소식이 전해졌다. PinkPantheress Met Her Opp At Disney World",
        "url": "https://stereogum.com/2497514/pinkpantheress-met-her-opp-at-disney-world/news/",
        "published_date": "2026-04-30 19:44:13",
        "category": "interview",
        "source": "www.stereogum.com"
      },
      {
        "title": "Alissa White-Gluz Names Her Top Three Vocalists of All Time",
        "summary": "Alissa가 음악 차트에서 주목할 만한 성과를 기록했다. 상업적 성공을 입증하는 결과다.",
        "url": "https://consequence.net/2026/04/alissa-white-gluz-top-three-vocalists-all-time/",
        "published_date": "2026-04-30 19:18:33",
        "category": "interview",
        "source": "consequenceofsound.net"
      },
      {
        "title": "Bruce Springsteen Brings A Rock Revolution to Chicago: Review + Photos",
        "summary": "Bruce와 관련된 주요 음악 업계 소식이 전해졌다. Bruce Springsteen Brings A Rock Revolution to Chicago: Revie...",
        "url": "https://consequence.net/2026/04/bruce-springsteen-chicago-concert-review-photos/",
        "published_date": "2026-04-30 19:00:27",
        "category": "interview",
        "source": "consequenceofsound.net"
      },
      {
        "title": "Korn’s Ra Diaz Reunited With 15 Stolen Bass Guitars Thanks to Community Effort",
        "summary": "Korn’s와 관련된 주요 음악 업계 소식이 전해졌다. Korn’s Ra Diaz Reunited With 15 Stolen Bass Guitars Thanks t...",
        "url": "https://consequence.net/2026/04/korn-ra-diaz-15-reunited-stolen-bass-guitars/",
        "published_date": "2026-04-30 18:38:32",
        "category": "interview",
        "source": "consequenceofsound.net"
      },
      {
        "title": "Foo Fighters Serve Up Blood, Guts, and Rock and Roll in New Zombie-Filled ‘Spit Shine’ Video",
        "summary": "Foo와 관련된 주요 음악 업계 소식이 전해졌다. Foo Fighters Serve Up Blood, Guts, and Rock and Roll in New ...",
        "url": "https://www.rollingstone.com/music/music-news/foo-fighters-spit-shine-music-video-zombies-1235556295/",
        "published_date": "2026-04-30 18:28:34",
        "category": "interview",
        "source": "www.rollingstone.com"
      },
      {
        "title": "Jpegmafia Announces Tour and New Album Experimental Rap",
        "summary": "Jpegmafia가 새 앨범 발매 소식을 공개했다. 이번 릴리스는 팬들과 음악 업계의 큰 관심을 받고 있다.",
        "url": "https://pitchfork.com/news/jpegmafia-announces-tour-and-new-album-experimental-rap/",
        "published_date": "2026-04-30 18:12:38",
        "category": "interview",
        "source": "pitchfork.com"
      },
      {
        "title": "Here’s Nick Cave’s blunt verdict on Russell Brand’s new Christianity conversion book",
        "summary": "Here’s와 관련된 주요 음악 업계 소식이 전해졌다. Here’s Nick Cave’s blunt verdict on Russell Brand’s new Chri...",
        "url": "https://www.nme.com/news/music/heres-nick-caves-blunt-verdict-on-russell-brands-new-christianity-conversion-book-3943416?utm_source=rss&utm_medium=rss&utm_campaign=heres-nick-caves-blunt-verdict-on-russell-brands-new-christianity-conversion-book",
        "published_date": "2026-04-30 18:11:54",
        "category": "interview",
        "source": "www.nme.com"
      },
      {
        "title": "In Q1, YouTube Music and Premium saw ‘largest quarterly increase’ in non-trial subscribers since 2018 launch, says Alphabet CEO, as platform’s quarterly ad revenues rose to $9.88B",
        "summary": "In와 관련된 주요 음악 업계 소식이 전해졌다. In Q1, YouTube Music and Premium saw ‘largest quarterly incr...",
        "url": "https://www.musicbusinessworldwide.com/youtube-music-and-premium-saw-largest-quarterly-increase-in-non-trial-subscribers-since-2018-launch-says-alphabet-ceo-as-platforms-ad-revenues-rose-to-9-88b/",
        "published_date": "2026-04-30 18:06:48",
        "category": "interview",
        "source": "www.musicbusinessworldwide.com"
      },
      {
        "title": "Tony Wilson, Hot Chocolate Bassist and Songwriter, Dead at 89",
        "summary": "Tony와 관련된 주요 음악 업계 소식이 전해졌다. Tony Wilson, Hot Chocolate Bassist and Songwriter, Dead at 8...",
        "url": "https://www.rollingstone.com/music/music-news/hot-chocolate-tony-wilson-you-sexy-thing-dead-obituary-1235556226/",
        "published_date": "2026-04-30 17:51:02",
        "category": "interview",
        "source": "www.rollingstone.com"
      },
      {
        "title": "J McClendon Gives First Interview About End Of Glass Beach And Launch Of New Band You Are An Angel",
        "summary": "J McClendon와 관련된 주요 음악 업계 소식이 전해졌다. J McClendon Gives First Interview About End Of Glass Beach A...",
        "url": "https://stereogum.com/2497501/j-mcclendon-gives-first-interview-about-end-of-glass-beach-and-launch-of-new-band-you-are-an-angel/music/",
        "published_date": "2026-04-30 17:47:08",
        "category": "interview",
        "source": "www.stereogum.com"
      },
      {
        "title": "Tech startup Nebula partners with Ghazi Shami’s Supply Chain to launch what it calls an ‘earn-before-you-stream’ music distro service",
        "summary": "Tech와 관련된 주요 음악 업계 소식이 전해졌다. Tech startup Nebula partners with Ghazi Shami’s Supply Chain...",
        "url": "https://www.musicbusinessworldwide.com/tech-startup-nebula-partners-with-ghazi-shamis-supply-chain-to-launch-what-it-calls-an-earn-before-you-stream-music-distro-service/",
        "published_date": "2026-04-30 17:34:30",
        "category": "interview",
        "source": "www.musicbusinessworldwide.com"
      },
      {
        "title": "Mike D Performs Beastie Boys Songs with Sons During Surprise Gig: Watch",
        "summary": "Mike와 관련된 주요 음악 업계 소식이 전해졌다. Mike D Performs Beastie Boys Songs with Sons During Surprise...",
        "url": "https://consequence.net/2026/04/mike-d-beastie-boys-sons-surprise-performance/",
        "published_date": "2026-04-30 16:50:19",
        "category": "interview",
        "source": "consequenceofsound.net"
      },
      {
        "title": "Madeon Announces New Album Victory: Hear “Fire Away” (Feat. Slayyyter)",
        "summary": "Madeon가 새 앨범 발매 소식을 공개했다. 팬들과 업계의 큰 관심을 받고 있다.",
        "url": "https://stereogum.com/2497496/madeon-announces-new-album-victory-hear-fire-away-feat-slayyyter/music/",
        "published_date": "2026-04-30 16:35:32",
        "category": "interview",
        "source": "www.stereogum.com"
      },
      {
        "title": "Madeon Launches New Album With Slayyyter Collaboration",
        "summary": "Madeon Launches가 새 앨범 발매 소식을 공개했다. 이번 릴리스는 팬들과 음악 업계의 큰 관심을 받고 있다.",
        "url": "https://pitchfork.com/news/madeon-launches-new-album-with-slayyyter-collaboration/",
        "published_date": "2026-04-30 16:26:37",
        "category": "interview",
        "source": "pitchfork.com"
      },
      {
        "title": "There’s Nothing Funny About Bleachers’ New Single ‘I’m Not Joking’",
        "summary": "There’s와 관련된 주요 음악 업계 소식이 전해졌다. There’s Nothing Funny About Bleachers’ New Single ‘I’m Not J...",
        "url": "https://www.rollingstone.com/music/music-news/bleachers-im-not-joking-new-song-everyone-for-ten-minutes-1235556201/",
        "published_date": "2026-04-30 16:25:26",
        "category": "interview",
        "source": "www.rollingstone.com"
      },
      {
        "title": "Bleachers Share “i’m not joking,” Jack Antonoff Addresses Not Working On Latest Taylor Swift Album",
        "summary": "Bleachers와 관련된 주요 음악 업계 소식이 전해졌다. Bleachers Share “i’m not joking,” Jack Antonoff Addresses No...",
        "url": "https://stereogum.com/2497483/bleachers-share-im-not-joking-jack-antonoff-addresses-not-working-on-latest-taylor-swift-album/music/",
        "published_date": "2026-04-30 16:21:43",
        "category": "interview",
        "source": "www.stereogum.com"
      },
      {
        "title": "Ex-Spandau Ballet singer Ross Davidson sentenced to 14 years for rape and sexual assault",
        "summary": "Ex-Spandau와 관련된 주요 음악 업계 소식이 전해졌다. Ex-Spandau Ballet singer Ross Davidson sentenced to 14 years...",
        "url": "https://www.nme.com/news/music/ex-spandau-ballet-singer-ross-davidson-sentenced-to-14-years-for-rape-and-sexual-assault-3943401?utm_source=rss&utm_medium=rss&utm_campaign=ex-spandau-ballet-singer-ross-davidson-sentenced-to-14-years-for-rape-and-sexual-assault",
        "published_date": "2026-04-30 16:20:28",
        "category": "interview",
        "source": "www.nme.com"
      },
      {
        "title": "Lizzy Rain Wins First WWE NXT Match with Iron Maiden Scream and AC/DC-Inspired Finisher: Watch",
        "summary": "Lizzy와 관련된 주요 음악 업계 소식이 전해졌다. Lizzy Rain Wins First WWE NXT Match with Iron Maiden Scream ...",
        "url": "https://consequence.net/2026/04/lizzy-rain-first-wwe-nxt-match-iron-maiden-scream-ac-dc-finisher/",
        "published_date": "2026-04-30 16:14:26",
        "category": "interview",
        "source": "consequenceofsound.net"
      },
      {
        "title": "Cusk – “Blue Tac Piano”",
        "summary": "Cusk와 관련된 주요 음악 업계 소식이 전해졌다. Cusk – “Blue Tac Piano”",
        "url": "https://stereogum.com/2497492/cusk-blue-tac-piano/music/",
        "published_date": "2026-04-30 16:09:14",
        "category": "interview",
        "source": "www.stereogum.com"
      },
      {
        "title": "Interpol Announce 2026 North American Tour",
        "summary": "Interpol의 라이브 공연 관련 소식이 전해졌다. 콘서트 티켓과 일정 정보가 업데이트되었다.",
        "url": "https://consequence.net/2026/04/interpol-2026-north-american-tour/",
        "published_date": "2026-04-30 16:06:35",
        "category": "interview",
        "source": "consequenceofsound.net"
      },
      {
        "title": "Train’s Pat Monahan Names His Five Favorite Vocalists of All Time",
        "summary": "Train’s와 관련된 주요 음악 업계 소식이 전해졌다. Train’s Pat Monahan Names His Five Favorite Vocalists of All...",
        "url": "https://consequence.net/2026/04/train-pat-monahan-five-favorite-vocalists/",
        "published_date": "2026-04-30 16:00:32",
        "category": "interview",
        "source": "consequenceofsound.net"
      },
      {
        "title": "Believe and TuneCore are blocking distribution of Generative AI tracks made on ‘pirate studios’ like Suno – while inking new partnerships with ElevenLabs and Udio",
        "summary": "Believe와 관련된 주요 음악 업계 소식이 전해졌다. Believe and TuneCore are blocking distribution of Generative...",
        "url": "https://www.musicbusinessworldwide.com/believe-and-tunecore-blocking-suno-elevenlabs-and-udio/",
        "published_date": "2026-04-30 15:54:48",
        "category": "interview",
        "source": "www.musicbusinessworldwide.com"
      }
    ],
    "insight": []
  },
  "summary": {
    "total_count": 50,
    "by_category": {
      "interview": 50
    },
    "by_source": {
      "www.stereogum.com": 11,
      "www.billboard.com": 10,
      "consequenceofsound.net": 10,
      "www.rollingstone.com": 7,
      "pitchfork.com": 6,
      "www.nme.com": 3,
      "www.musicbusinessworldwide.com": 3
    },
    "members_only_count": 0
  }
}