{
  "metadata": {
    "generated_at": "2025-09-13T02:12:14.051764",
    "total_news": 50,
    "last_updated": "2025-09-13T02:12:14.051773",
    "version": "2.0",
    "compatible_with": "NewsSection.tsx"
  },
  "news": {
    "all_articles": [],
    "news": [],
    "interview": [
      {
        "title": "Every 2025 Caribbean Music Awards Performance, Ranked",
        "summary": "Every와 관련된 주요 음악 업계 소식이 전해졌다. Every 2025 Caribbean Music Awards Performance, Ranked",
        "url": "https://www.billboard.com/lists/2025-caribbean-music-awards-performances-ranked-lady-lava/",
        "published_date": "2025-09-13 02:00:00",
        "category": "interview",
        "source": "www.billboard.com"
      },
      {
        "title": "Snubs & Surprises at 2025 Caribbean Music Awards: Chronic Law, Bunji Garlin & Jada Kingdom Shut Out",
        "summary": "Snubs와 관련된 주요 음악 업계 소식이 전해졌다. Snubs & Surprises at 2025 Caribbean Music Awards: Chronic La...",
        "url": "https://www.billboard.com/lists/snubs-surprises-2025-caribbean-music-awards-chronic-law/",
        "published_date": "2025-09-13 02:00:00",
        "category": "interview",
        "source": "www.billboard.com"
      },
      {
        "title": "Machel Montano & Ayetian Make Surprise Appearance at 2025 Caribbean Music Awards: 6 Best Moments",
        "summary": "Machel와 관련된 주요 음악 업계 소식이 전해졌다. Machel Montano & Ayetian Make Surprise Appearance at 2025 Ca...",
        "url": "https://www.billboard.com/lists/2025-caribbean-music-awards-best-moments-rihanna-machel/",
        "published_date": "2025-09-13 02:00:00",
        "category": "interview",
        "source": "www.billboard.com"
      },
      {
        "title": "Bad Bunny, Shenseea & Vybz Kartel Triumph at 2025 Caribbean Music Awards: See Complete Winners List",
        "summary": "Bad와 관련된 주요 음악 업계 소식이 전해졌다. Bad Bunny, Shenseea & Vybz Kartel Triumph at 2025 Caribbean ...",
        "url": "https://www.billboard.com/music/awards/2025-caribbean-music-awards-winners-list-bad-bunny-shenseea-1236063073/",
        "published_date": "2025-09-13 02:00:00",
        "category": "interview",
        "source": "www.billboard.com"
      },
      {
        "title": "Taylor Swift Deposition Off Limits to Justin Baldoni, Judge Rules: Lack of ‘Appropriate Diligence’",
        "summary": "Taylor와 관련된 주요 음악 업계 소식이 전해졌다. Taylor Swift Deposition Off Limits to Justin Baldoni, Judge ...",
        "url": "https://www.rollingstone.com/music/music-news/taylor-swift-deposition-denied-justin-baldoni-1235426835/",
        "published_date": "2025-09-13 01:47:58",
        "category": "interview",
        "source": "www.rollingstone.com"
      },
      {
        "title": "Sharon Osbourne Thanks Fans for ‘Overwhelming Love’ After Ozzy’s Death",
        "summary": "Sharon와 관련된 주요 음악 업계 소식이 전해졌다. Sharon Osbourne Thanks Fans for ‘Overwhelming Love’ After Oz...",
        "url": "https://www.rollingstone.com/music/music-news/sharon-osbourne-ozzy-osbourne-death-thanks-fans-1235426832/",
        "published_date": "2025-09-13 00:50:14",
        "category": "interview",
        "source": "www.rollingstone.com"
      },
      {
        "title": "Song of the Week: Spinal Tap Enlist Paul McCartney for the Downright Joyous “Cups and Cakes”",
        "summary": "Song와 관련된 주요 음악 업계 소식이 전해졌다. Song of the Week: Spinal Tap Enlist Paul McCartney for the D...",
        "url": "https://consequence.net/2025/09/spinal-tap-cups-and-cakes-paul-mccartney/",
        "published_date": "2025-09-13 00:34:09",
        "category": "interview",
        "source": "consequenceofsound.net"
      },
      {
        "title": "Sphere Stock Continues to Soar, Gaining 46% in Last 4 Weeks on ‘Wizard of Oz’ Success",
        "summary": "Sphere와 관련된 주요 음악 업계 소식이 전해졌다. Sphere Stock Continues to Soar, Gaining 46% in Last 4 Weeks ...",
        "url": "https://www.billboard.com/pro/sphere-stock-wizard-of-oz-gains-up/",
        "published_date": "2025-09-13 00:08:57",
        "category": "interview",
        "source": "www.billboard.com"
      },
      {
        "title": "In Canada: The Beaches Named Billboard Canada’s Women of the Year 2025",
        "summary": "In와 관련된 주요 음악 업계 소식이 전해졌다. In Canada: The Beaches Named Billboard Canada’s Women of the...",
        "url": "https://www.billboard.com/pro/the-beaches-billboard-canada-women-of-the-year/",
        "published_date": "2025-09-12 23:53:50",
        "category": "interview",
        "source": "www.billboard.com"
      },
      {
        "title": "Hunting for the Next HUNTR/X: Galaxy Corporation Holds L.A. Auditions for Virtual K-Pop Group",
        "summary": "Hunting와 관련된 주요 음악 업계 소식이 전해졌다. Hunting for the Next HUNTR/X: Galaxy Corporation Holds L.A. ...",
        "url": "https://www.billboard.com/business/tech/virtual-kpop-group-galaxy-corporation-la-auditions-1236064288/",
        "published_date": "2025-09-12 23:32:00",
        "category": "interview",
        "source": "www.billboard.com"
      },
      {
        "title": "Kansas City Chiefs vs. Philadelphia Eagles: How to Watch 2025 Super Bowl Rematch Online",
        "summary": "Kansas와 관련된 주요 음악 업계 소식이 전해졌다. Kansas City Chiefs vs. Philadelphia Eagles: How to Watch 202...",
        "url": "https://www.billboard.com/culture/product-recommendations/kansas-city-chiefs-philadelphia-eagles-watch-online-1236065916/",
        "published_date": "2025-09-12 23:04:50",
        "category": "interview",
        "source": "www.billboard.com"
      },
      {
        "title": "Akon’s Wife Files for Divorce After 29 Years of Marriage",
        "summary": "Akon’s와 관련된 주요 음악 업계 소식이 전해졌다. Akon’s Wife Files for Divorce After 29 Years of Marriage",
        "url": "https://www.billboard.com/music/rb-hip-hop/akon-divorce-tameka-thiam-files-29-years-marriage-1236065967/",
        "published_date": "2025-09-12 23:01:02",
        "category": "interview",
        "source": "www.billboard.com"
      },
      {
        "title": "Tate McRae Welcomes Megan Moroney for Duet of ‘6 Months Later’ at Nashville Show",
        "summary": "Tate와 관련된 주요 음악 업계 소식이 전해졌다. Tate McRae Welcomes Megan Moroney for Duet of ‘6 Months Late...",
        "url": "https://www.rollingstone.com/music/music-news/tate-mcrae-megan-moroney-duet-6-months-later-nashville-show-1235426794/",
        "published_date": "2025-09-12 22:47:06",
        "category": "interview",
        "source": "www.rollingstone.com"
      },
      {
        "title": "Mexican Cuisine, Orchestral Sounds & ‘Mutual Appreciation’ of New Generation: How David Byrne Created His ‘Who Is the Sky?’ Album",
        "summary": "Mexican와 관련된 주요 음악 업계 소식이 전해졌다. Mexican Cuisine, Orchestral Sounds & ‘Mutual Appreciation’ o...",
        "url": "https://www.billboard.com/music/rock/david-byrne-new-album-who-is-the-sky-interview-1236065932/",
        "published_date": "2025-09-12 22:19:11",
        "category": "interview",
        "source": "www.billboard.com"
      },
      {
        "title": "Paramount Denounces Boycott of Israeli Film Institutions",
        "summary": "Paramount와 관련된 주요 음악 업계 소식이 전해졌다. Paramount Denounces Boycott of Israeli Film Institutions",
        "url": "https://consequence.net/2025/09/paramount-israeli-boycott/",
        "published_date": "2025-09-12 21:28:22",
        "category": "interview",
        "source": "consequenceofsound.net"
      },
      {
        "title": "Kanye West Ex-Employee Gets $76K in Legal Fees for Musician’s ‘Frivolous’ Motion to Sink Her Lawsuit",
        "summary": "Kanye와 관련된 주요 음악 업계 소식이 전해졌다. Kanye West Ex-Employee Gets $76K in Legal Fees for Musician’...",
        "url": "https://www.rollingstone.com/music/music-news/kanye-west-ex-employee-antisemitic-harassment-lawsuit-1235426675/",
        "published_date": "2025-09-12 21:28:15",
        "category": "interview",
        "source": "www.rollingstone.com"
      },
      {
        "title": "Daniel Day-Lewis “Never Intended” Retirement from Acting: “I Just Wanted to Work on Something Else for a While”",
        "summary": "Daniel와 관련된 주요 음악 업계 소식이 전해졌다. Daniel Day-Lewis “Never Intended” Retirement from Acting: “I...",
        "url": "https://consequence.net/2025/09/daniel-day-lewis-retirement-comments/",
        "published_date": "2025-09-12 21:21:37",
        "category": "interview",
        "source": "consequenceofsound.net"
      },
      {
        "title": "Mötley Crüe’s Vince Neil Suffered Stroke Last December: ‘I Had to Learn to Walk Again’",
        "summary": "Mötley와 관련된 주요 음악 업계 소식이 전해졌다. Mötley Crüe’s Vince Neil Suffered Stroke Last December: ‘I H...",
        "url": "https://www.rollingstone.com/music/music-news/motley-crue-vince-neil-stroke-1235426749/",
        "published_date": "2025-09-12 21:10:56",
        "category": "interview",
        "source": "www.rollingstone.com"
      },
      {
        "title": "Djo Just Dropped His Second Album Of 2025",
        "summary": "배우 겸 음악가 조 케리(Djo)가 2025년 두 번째 정규 앨범 'The Crux Deluxe'를 깜짝 발매했다.  지난 4월 발표한 첫 번째 앨범 'The Crux'에 이어 불과 몇 개월 만에 새 앨범을 선보인 것.  이번 앨범에는 지난주부터 선공개된 싱글 \"Carry The Name\" 등 총 12곡이 수록되었다.",
        "url": "https://www.stereogum.com/2322853/djo-just-dropped-his-second-album-of-2025/music/",
        "published_date": "2025-09-12 21:04:20",
        "category": "interview",
        "source": "www.stereogum.com"
      },
      {
        "title": "John Fogerty Bringing CCR Classics to Las Vegas Residency",
        "summary": "John와 관련된 주요 음악 업계 소식이 전해졌다. John Fogerty Bringing CCR Classics to Las Vegas Residency",
        "url": "https://consequence.net/2025/09/john-fogerty-ccr-las-vegas-residency/",
        "published_date": "2025-09-12 20:54:20",
        "category": "interview",
        "source": "consequenceofsound.net"
      },
      {
        "title": "Sink Your Teeth Into Cafuné’s New Album Bite Reality",
        "summary": "Sink와 관련된 주요 음악 업계 소식이 전해졌다. Sink Your Teeth Into Cafuné’s New Album Bite Reality",
        "url": "https://www.stereogum.com/2322845/sink-your-teeth-into-cafunes-new-album-bite-reality/music/",
        "published_date": "2025-09-12 20:29:36",
        "category": "interview",
        "source": "www.stereogum.com"
      },
      {
        "title": "Neil Young and the Chrome Hearts Sued by Luxury Brand Chrome Hearts",
        "summary": "Neil와 관련된 주요 음악 업계 소식이 전해졌다. Neil Young and the Chrome Hearts Sued by Luxury Brand Chrome...",
        "url": "https://www.rollingstone.com/music/music-news/neil-young-chrome-hearts-trademark-infringement-lawsuit-1235426674/",
        "published_date": "2025-09-12 20:26:36",
        "category": "interview",
        "source": "www.rollingstone.com"
      },
      {
        "title": "Yves Tumor Rips Swedish House Mafia Fans as “Corniest People” After Being Booed Offstage",
        "summary": "Yves와 관련된 주요 음악 업계 소식이 전해졌다. Yves Tumor Rips Swedish House Mafia Fans as “Corniest People...",
        "url": "https://consequence.net/2025/09/yves-tumor-swedish-house-mafia-fans/",
        "published_date": "2025-09-12 20:26:14",
        "category": "interview",
        "source": "consequenceofsound.net"
      },
      {
        "title": "Mötley Crüe’s Vince Neil Reveals He Suffered a Stroke Last Christmas",
        "summary": "Mötley가 중요한 음악 관련 발표를 했다. 이번 소식은 팬들의 주목을 받고 있다.",
        "url": "https://consequence.net/2025/09/motley-crue-vince-neil-suffered-stroke/",
        "published_date": "2025-09-12 20:07:36",
        "category": "interview",
        "source": "consequenceofsound.net"
      },
      {
        "title": "Luh Tyler – “Young Player” (Feat. Larry June)",
        "summary": "Luh의 새로운 협업 프로젝트 소식이 공개되었다. 음악 팬들의 기대감이 높아지고 있다.",
        "url": "https://www.stereogum.com/2322842/luh-tyler-young-player-feat-larry-june/music/",
        "published_date": "2025-09-12 20:04:43",
        "category": "interview",
        "source": "www.stereogum.com"
      },
      {
        "title": "Watch Sarah McLachlan, Olivia Rodrigo Discuss Lilith Fair’s Impact in New Doc Trailer",
        "summary": "Watch와 관련된 주요 음악 업계 소식이 전해졌다. Watch Sarah McLachlan, Olivia Rodrigo Discuss Lilith Fair’s ...",
        "url": "https://www.rollingstone.com/music/music-news/lilith-fair-documentary-trailer-1235426604/",
        "published_date": "2025-09-12 19:43:50",
        "category": "interview",
        "source": "www.rollingstone.com"
      },
      {
        "title": "dEUS to play classics ‘Worst Case Scenario’ and ‘In A Bar, Under The Sea’ in full on 30th anniversary 2026 UK and European tour",
        "summary": "dEUS의 라이브 공연 관련 소식이 전해졌다. 콘서트 티켓과 일정 정보가 업데이트되었다.",
        "url": "https://www.nme.com/news/music/deus-to-play-classics-worst-case-scenario-and-in-a-bar-under-the-sea-in-full-on-30th-anniversary-2026-uk-and-european-tour-3892362?utm_source=rss&utm_medium=rss&utm_campaign=deus-to-play-classics-worst-case-scenario-and-in-a-bar-under-the-sea-in-full-on-30th-anniversary-2026-uk-and-european-tour",
        "published_date": "2025-09-12 19:36:51",
        "category": "interview",
        "source": "www.nme.com"
      },
      {
        "title": "Watch Charly Bliss Debut New Song “Madrid” And Cover Yellowcard On NYC Concert Cruise",
        "summary": "뉴욕 출신 인디 팝 록 밴드 Charly Bliss가 9월 11일 자유의 여신상 주변을 돌며 공연을 펼쳤습니다.  이번 공연에서 밴드는 새로운 곡 \"Madrid\"를 데뷔 무대에 올렸고, 옐로카드의 \"Ocean Avenue\"를 커버하는 등 다채로운 무대를 선보였습니다.",
        "url": "https://www.stereogum.com/2322837/watch-charly-bliss-debut-new-song-madrid-and-cover-yellowcard-on-nyc-concert-cruise/news/",
        "published_date": "2025-09-12 19:30:42",
        "category": "interview",
        "source": "www.stereogum.com"
      },
      {
        "title": "Cash Cobain Lights Up Brooklyn at Weedmaps’ Kickback Event: Recap + Photos",
        "summary": "Cash와 관련된 주요 음악 업계 소식이 전해졌다. Cash Cobain Lights Up Brooklyn at Weedmaps’ Kickback Event: ...",
        "url": "https://consequence.net/2025/09/cash-cobain-brooklyn-weedmaps-kickback/",
        "published_date": "2025-09-12 19:11:46",
        "category": "interview",
        "source": "consequenceofsound.net"
      },
      {
        "title": "Radioactivity Announce New Album Time Won’t Bring Me Down: Hear The Title Track",
        "summary": "텍사스 출신의 가라지 펑크 밴드 Radioactivity가 2015년 2집 'Silent Kill' 이후 10년 만에 새 앨범 'Time Won't Bring Me Down'을 발표할 예정입니다.",
        "url": "https://www.stereogum.com/2322833/radioactivity-announce-new-album-time-wont-bring-me-down-hear-the-title-track/music/",
        "published_date": "2025-09-12 19:09:24",
        "category": "interview",
        "source": "www.stereogum.com"
      },
      {
        "title": "Frog – “SAX-A-MA-PHONE VAR. XII”",
        "summary": "뉴욕 출신의 인디 밴드 Frog가 왕성한 활동을 보이고 있습니다. Frog는 올해 초 발표한 '1000 Variations On The Same Song'에 이어 내주 두 번째 앨범 'The Count'를 발매할 예정입니다. 이번 앨범은 지난달 뉴욕 시내에 출현했다는 미스터리한 인물을 주제로 한 컨셉 앨범입니다.",
        "url": "https://www.stereogum.com/2322824/frog-sax-a-ma-phone-var-xii/music/",
        "published_date": "2025-09-12 19:03:09",
        "category": "interview",
        "source": "www.stereogum.com"
      },
      {
        "title": "The 5 Best Songs Of The Week",
        "summary": "매주 스테레오검 편집진은 그 주의 5개 최고의 신곡을 선정합니다.",
        "url": "https://www.stereogum.com/2322699/the-5-best-songs-of-the-week-595/lists/the-5-best-songs-of-the-week/",
        "published_date": "2025-09-12 19:00:32",
        "category": "interview",
        "source": "www.stereogum.com"
      },
      {
        "title": "The Who Announce Final Show of North American Farewell Tour",
        "summary": "The의 라이브 공연 관련 소식이 전해졌다. 콘서트 티켓과 일정 정보가 업데이트되었다.",
        "url": "https://consequence.net/2025/09/the-who-final-show-north-american-farewell-tour/",
        "published_date": "2025-09-12 18:52:28",
        "category": "interview",
        "source": "consequenceofsound.net"
      },
      {
        "title": "Stream JADE’s Ambitious, Fired-Up Solo Debut That’s Showbiz Baby!",
        "summary": "영국 출신 가수 JADE가 자신의 첫 번째 솔로 앨범 'That's Showbiz Baby!'를 발매했다.  JADE는 지난 2022년 여성 아이돌 그룹 리틀믹스의 멤버로 활동하다 그룹의 활동 휴식기를 맞이했다.  약 1년 전 JADE는 솔로 싱글 \"Angel Of My Dreams\"를 발표하며 독립 아티스트로서의 행보를 시작했다.",
        "url": "https://www.stereogum.com/2322825/stream-jades-ambitious-fired-up-solo-debut-thats-showbiz-baby/music/",
        "published_date": "2025-09-12 18:50:07",
        "category": "interview",
        "source": "www.stereogum.com"
      },
      {
        "title": "Limp Bizkit Know How to Get Your Attention With New Song ‘Making Love to Morgan Wallen’",
        "summary": "Limp와 관련된 주요 음악 업계 소식이 전해졌다. Limp Bizkit Know How to Get Your Attention With New Song ‘Ma...",
        "url": "https://www.rollingstone.com/music/music-news/limp-bizkit-new-song-making-love-to-morgan-wallen-1235426548/",
        "published_date": "2025-09-12 18:45:33",
        "category": "interview",
        "source": "www.rollingstone.com"
      },
      {
        "title": "Taylor Swift Has Not Agreed to Deposition in Blake Lively, Justin Baldoni Case — But She May Be ‘Forced’",
        "summary": "Taylor의 라이브 공연 관련 소식이 전해졌다. 콘서트 티켓과 일정 정보가 업데이트되었다.",
        "url": "https://www.rollingstone.com/music/music-news/taylor-swift-blake-lively-lawsuit-justin-baldoni-deposition-1235426306/",
        "published_date": "2025-09-12 18:41:14",
        "category": "interview",
        "source": "www.rollingstone.com"
      },
      {
        "title": "Djo shares new “companion piece” album to ‘The Crux’ with 12 new songs",
        "summary": "Djo와 관련된 주요 음악 업계 소식이 전해졌다. Djo shares new “companion piece” album to ‘The Crux’ with 12...",
        "url": "https://www.nme.com/news/music/djo-shares-new-companion-piece-album-to-the-crux-with-12-new-songs-3892358?utm_source=rss&utm_medium=rss&utm_campaign=djo-shares-new-companion-piece-album-to-the-crux-with-12-new-songs",
        "published_date": "2025-09-12 18:38:31",
        "category": "interview",
        "source": "www.nme.com"
      },
      {
        "title": "Little Simz – “Don’t Leave Too Soon”",
        "summary": "Little와 관련된 주요 음악 업계 소식이 전해졌다. Little Simz – “Don’t Leave Too Soon”",
        "url": "https://www.stereogum.com/2322820/little-simz-dont-leave-too-soon/music/",
        "published_date": "2025-09-12 18:29:12",
        "category": "interview",
        "source": "www.stereogum.com"
      },
      {
        "title": "Jane Remover Shares “Dreamflasher” Video and New Song Featuring Lucy Bedroque: Watch",
        "summary": "Jane의 새로운 협업 프로젝트 소식이 공개되었다. 음악 팬들의 기대감이 높아지고 있다.",
        "url": "https://pitchfork.com/news/jane-remover-shares-dreamflasher-video-and-new-song-featuring-lucy-bedroque-watch",
        "published_date": "2025-09-12 17:53:28",
        "category": "interview",
        "source": "pitchfork.com"
      },
      {
        "title": "Flea’s Silverlake Conservatory Students Release Red Hot Chili Peppers Tribute EP: Stream",
        "summary": "Flea’s와 관련된 주요 음악 업계 소식이 전해졌다. Flea’s Silverlake Conservatory Students Release Red Hot Chil...",
        "url": "https://consequence.net/2025/09/flea-silverlake-conservatory-students-red-hot-chili-peppers-tribute-ep/",
        "published_date": "2025-09-12 17:17:38",
        "category": "interview",
        "source": "consequenceofsound.net"
      },
      {
        "title": "Jeff Tweedy – “Lou Reed Was My Babysitter”",
        "summary": "Jeff와 관련된 주요 음악 업계 소식이 전해졌다. Jeff Tweedy – “Lou Reed Was My Babysitter”",
        "url": "https://www.stereogum.com/2322738/jeff-tweedy-lou-reed-was-my-babysitter/music/",
        "published_date": "2025-09-12 17:11:22",
        "category": "interview",
        "source": "www.stereogum.com"
      },
      {
        "title": "Ed Sheeran Celebrates ‘Play’ With Live Tiny Desk Concert",
        "summary": "Ed의 라이브 공연 관련 소식이 전해졌다. 콘서트 티켓과 일정 정보가 업데이트되었다.",
        "url": "https://www.rollingstone.com/music/music-news/ed-sheeran-performs-play-live-tiny-desk-1235426343/",
        "published_date": "2025-09-12 17:01:26",
        "category": "interview",
        "source": "www.rollingstone.com"
      },
      {
        "title": "Stereolab Release New Songs “Fed Up With Your Job” and “Constant and Uniform Movement Unknown”: Listen",
        "summary": "영국 밴드 Stereolab이 새로운 더블 A사이드 싱글 \"Fed Up With Your Job\"과 \"Constant and Uniform Movement Unknown\"을 발표했습니다.  이번 싱글은 지난 5월 발매된 컴백 앨범 이후 Stereolab의 첫 신곡 작품입니다.",
        "url": "https://pitchfork.com/news/stereolab-release-new-songs-fed-up-with-your-job-and-constant-and-uniform-movement-unknown-listen",
        "published_date": "2025-09-12 17:00:07",
        "category": "interview",
        "source": "pitchfork.com"
      },
      {
        "title": "Jeff Tweedy Shares Video for New Song “Lou Reed Was My Babysitter”: Watch",
        "summary": "Jeff와 관련된 주요 음악 업계 소식이 전해졌다. Jeff Tweedy Shares Video for New Song “Lou Reed Was My Babys...",
        "url": "https://pitchfork.com/news/jeff-tweedy-shares-video-for-new-song-lou-reed-was-my-babysitter-watch",
        "published_date": "2025-09-12 16:57:54",
        "category": "interview",
        "source": "pitchfork.com"
      },
      {
        "title": "Heavy Song of the Week: HEALTH Channel Anger and Fear on “ORDINARY LOSS”",
        "summary": "Heavy와 관련된 주요 음악 업계 소식이 전해졌다. Heavy Song of the Week: HEALTH Channel Anger and Fear on “OR...",
        "url": "https://consequence.net/2025/09/heavy-song-of-the-week-health-ordinary-loss/",
        "published_date": "2025-09-12 16:26:47",
        "category": "interview",
        "source": "consequenceofsound.net"
      },
      {
        "title": "Luxury Fashion Brand Chrome Hearts Sues Neil Young",
        "summary": "가수 닐 영(Neil Young)이 지난 1년간 새로운 백업 밴드 '크롬 하츠(Chrome Hearts)'와 함께 투어와 녹음 활동을 해왔습니다.",
        "url": "https://www.stereogum.com/2322811/luxury-fashion-brand-chrome-hearts-sues-neil-young/news/",
        "published_date": "2025-09-12 16:17:30",
        "category": "interview",
        "source": "www.stereogum.com"
      },
      {
        "title": "Neil Young Sued by Chrome Hearts Fashion Brand Over New Band’s Name",
        "summary": "Neil와 관련된 주요 음악 업계 소식이 전해졌다. Neil Young Sued by Chrome Hearts Fashion Brand Over New Band...",
        "url": "https://pitchfork.com/news/neil-young-sued-by-chrome-hearts-fashion-brand-over-new-band-name",
        "published_date": "2025-09-12 16:15:36",
        "category": "interview",
        "source": "pitchfork.com"
      },
      {
        "title": "Limp Bizkit share ‘Making Love To Morgan Wallen’, their first single in four years",
        "summary": "Limp와 관련된 주요 음악 업계 소식이 전해졌다. Limp Bizkit share ‘Making Love To Morgan Wallen’, their firs...",
        "url": "https://www.nme.com/news/music/limp-bizkit-share-making-love-to-morgan-wallen-their-first-single-in-four-years-3892324?utm_source=rss&utm_medium=rss&utm_campaign=limp-bizkit-share-making-love-to-morgan-wallen-their-first-single-in-four-years",
        "published_date": "2025-09-12 16:11:45",
        "category": "interview",
        "source": "www.nme.com"
      },
      {
        "title": "From streaming’s AI problem to Spotify’s lossless launch… it’s MBW’s weekly round-up",
        "summary": "From와 관련된 주요 음악 업계 소식이 전해졌다. From streaming’s AI problem to Spotify’s lossless launch… it...",
        "url": "https://www.musicbusinessworldwide.com/from-streamings-ai-problem-to-spotifys-lossless-launch-its-mbws-weekly-round-up/",
        "published_date": "2025-09-12 16:00:08",
        "category": "interview",
        "source": "www.musicbusinessworldwide.com"
      },
      {
        "title": "LCD Soundsystem Announce 2025 NYC Residency",
        "summary": "LCD와 관련된 주요 음악 업계 소식이 전해졌다. LCD Soundsystem Announce 2025 NYC Residency",
        "url": "https://consequence.net/2025/09/lcd-soundsystem-2025-nyc-residency/",
        "published_date": "2025-09-12 15:55:15",
        "category": "interview",
        "source": "consequenceofsound.net"
      }
    ],
    "insight": []
  },
  "summary": {
    "total_count": 50,
    "by_category": {
      "interview": 50
    },
    "by_source": {
      "consequenceofsound.net": 11,
      "www.stereogum.com": 11,
      "www.billboard.com": 10,
      "www.rollingstone.com": 10,
      "pitchfork.com": 4,
      "www.nme.com": 3,
      "www.musicbusinessworldwide.com": 1
    },
    "members_only_count": 0
  }
}